<?xml version="1.0" encoding="utf-8" ?>
<Patch>

  <Operation Class="PatchOperationAddModExtension">
    <xpath>Defs/PawnKindDef[defName="BearManWarrior"]</xpath>
    <value>
      <li Class="CombatExtended.LoadoutPropertiesExtension">
        <primaryMagazineCount>
          <min>30</min>  <!-- single arrow count, not packs of arrows -->
          <max>50</max>
        </primaryMagazineCount>
      </li>
    </value>
  </Operation>

  <Operation Class="PatchOperationAddModExtension">
    <xpath>Defs/PawnKindDef[defName="BearManTrader"]</xpath>
    <value>
      <li Class="CombatExtended.LoadoutPropertiesExtension">
        <primaryMagazineCount>
          <min>30</min>  <!-- single arrow count, not packs of arrows -->
          <max>50</max>
        </primaryMagazineCount>
      </li>
    </value>
  </Operation>

  <Operation Class="PatchOperationAddModExtension">
    <xpath>Defs/PawnKindDef[defName="BearManArcher"]</xpath>
    <value>
      <li Class="CombatExtended.LoadoutPropertiesExtension">
        <primaryMagazineCount>
          <min>30</min>  <!-- single arrow count, not packs of arrows -->
          <max>50</max>
        </primaryMagazineCount>
      </li>
    </value>
  </Operation>

  <Operation Class="PatchOperationAddModExtension">
    <xpath>Defs/PawnKindDef[defName="BearManChief"]</xpath>
    <value>
      <li Class="CombatExtended.LoadoutPropertiesExtension">
        <primaryMagazineCount>
          <min>30</min>  <!-- single arrow count, not packs of arrows -->
          <max>50</max>
        </primaryMagazineCount>
      </li>
    </value>
  </Operation>

  <Operation Class="PatchOperationAddModExtension">
    <xpath>Defs/PawnKindDef[defName="CamelManWarrior"]</xpath>
    <value>
      <li Class="CombatExtended.LoadoutPropertiesExtension">
        <primaryMagazineCount>
          <min>30</min>  <!-- single arrow count, not packs of arrows -->
          <max>50</max>
        </primaryMagazineCount>
      </li>
    </value>
  </Operation>

  <Operation Class="PatchOperationAddModExtension">
    <xpath>Defs/PawnKindDef[defName="CamelManTrader"]</xpath>
    <value>
      <li Class="CombatExtended.LoadoutPropertiesExtension">
        <primaryMagazineCount>
          <min>30</min>  <!-- single arrow count, not packs of arrows -->
          <max>50</max>
        </primaryMagazineCount>
      </li>
    </value>
  </Operation>

  <Operation Class="PatchOperationAddModExtension">
    <xpath>Defs/PawnKindDef[defName="CamelManArcher"]</xpath>
    <value>
      <li Class="CombatExtended.LoadoutPropertiesExtension">
        <primaryMagazineCount>
          <min>30</min>  <!-- single arrow count, not packs of arrows -->
          <max>50</max>
        </primaryMagazineCount>
      </li>
    </value>
  </Operation>

  <Operation Class="PatchOperationAddModExtension">
    <xpath>Defs/PawnKindDef[defName="CamelManChief"]</xpath>
    <value>
      <li Class="CombatExtended.LoadoutPropertiesExtension">
        <primaryMagazineCount>
          <min>30</min>  <!-- single arrow count, not packs of arrows -->
          <max>50</max>
        </primaryMagazineCount>
      </li>
    </value>
  </Operation>

  <Operation Class="PatchOperationAddModExtension">
    <xpath>Defs/PawnKindDef[defName="ElephantManWarrior"]</xpath>
    <value>
      <li Class="CombatExtended.LoadoutPropertiesExtension">
        <primaryMagazineCount>
          <min>30</min>  <!-- single arrow count, not packs of arrows -->
          <max>50</max>
        </primaryMagazineCount>
      </li>
    </value>
  </Operation>

  <Operation Class="PatchOperationAddModExtension">
    <xpath>Defs/PawnKindDef[defName="ElephantManTrader"]</xpath>
    <value>
      <li Class="CombatExtended.LoadoutPropertiesExtension">
        <primaryMagazineCount>
          <min>30</min>  <!-- single arrow count, not packs of arrows -->
          <max>50</max>
        </primaryMagazineCount>
      </li>
    </value>
  </Operation>

  <Operation Class="PatchOperationAddModExtension">
    <xpath>Defs/PawnKindDef[defName="ElephantManArcher"]</xpath>
    <value>
      <li Class="CombatExtended.LoadoutPropertiesExtension">
        <primaryMagazineCount>
          <min>30</min>  <!-- single arrow count, not packs of arrows -->
          <max>50</max>
        </primaryMagazineCount>
      </li>
    </value>
  </Operation>

  <Operation Class="PatchOperationAddModExtension">
    <xpath>Defs/PawnKindDef[defName="ElephantManChief"]</xpath>
    <value>
      <li Class="CombatExtended.LoadoutPropertiesExtension">
        <primaryMagazineCount>
          <min>30</min>  <!-- single arrow count, not packs of arrows -->
          <max>50</max>
        </primaryMagazineCount>
      </li>
    </value>
  </Operation>

  <Operation Class="PatchOperationAddModExtension">
    <xpath>Defs/PawnKindDef[defName="ElkManWarrior"]</xpath>
    <value>
      <li Class="CombatExtended.LoadoutPropertiesExtension">
        <primaryMagazineCount>
          <min>30</min>  <!-- single arrow count, not packs of arrows -->
          <max>50</max>
        </primaryMagazineCount>
      </li>
    </value>
  </Operation>

  <Operation Class="PatchOperationAddModExtension">
    <xpath>Defs/PawnKindDef[defName="ElkManTrader"]</xpath>
    <value>
      <li Class="CombatExtended.LoadoutPropertiesExtension">
        <primaryMagazineCount>
          <min>30</min>  <!-- single arrow count, not packs of arrows -->
          <max>50</max>
        </primaryMagazineCount>
      </li>
    </value>
  </Operation>

  <Operation Class="PatchOperationAddModExtension">
    <xpath>Defs/PawnKindDef[defName="ElkManArcher"]</xpath>
    <value>
      <li Class="CombatExtended.LoadoutPropertiesExtension">
        <primaryMagazineCount>
          <min>30</min>  <!-- single arrow count, not packs of arrows -->
          <max>50</max>
        </primaryMagazineCount>
      </li>
    </value>
  </Operation>

  <Operation Class="PatchOperationAddModExtension">
    <xpath>Defs/PawnKindDef[defName="ElkManChief"]</xpath>
    <value>
      <li Class="CombatExtended.LoadoutPropertiesExtension">
        <primaryMagazineCount>
          <min>30</min>  <!-- single arrow count, not packs of arrows -->
          <max>50</max>
        </primaryMagazineCount>
      </li>
    </value>
  </Operation>

  <Operation Class="PatchOperationAddModExtension">
    <xpath>Defs/PawnKindDef[defName="FoxManWarrior"]</xpath>
    <value>
      <li Class="CombatExtended.LoadoutPropertiesExtension">
        <primaryMagazineCount>
          <min>30</min>  <!-- single arrow count, not packs of arrows -->
          <max>50</max>
        </primaryMagazineCount>
      </li>
    </value>
  </Operation>

  <Operation Class="PatchOperationAddModExtension">
    <xpath>Defs/PawnKindDef[defName="FoxManTrader"]</xpath>
    <value>
      <li Class="CombatExtended.LoadoutPropertiesExtension">
        <primaryMagazineCount>
          <min>30</min>  <!-- single arrow count, not packs of arrows -->
          <max>50</max>
        </primaryMagazineCount>
      </li>
    </value>
  </Operation>

  <Operation Class="PatchOperationAddModExtension">
    <xpath>Defs/PawnKindDef[defName="FoxManArcher"]</xpath>
    <value>
      <li Class="CombatExtended.LoadoutPropertiesExtension">
        <primaryMagazineCount>
          <min>30</min>  <!-- single arrow count, not packs of arrows -->
          <max>50</max>
        </primaryMagazineCount>
      </li>
    </value>
  </Operation>

  <Operation Class="PatchOperationAddModExtension">
    <xpath>Defs/PawnKindDef[defName="FoxManChief"]</xpath>
    <value>
      <li Class="CombatExtended.LoadoutPropertiesExtension">
        <primaryMagazineCount>
          <min>30</min>  <!-- single arrow count, not packs of arrows -->
          <max>50</max>
        </primaryMagazineCount>
      </li>
    </value>
  </Operation>

  <Operation Class="PatchOperationAddModExtension">
    <xpath>Defs/PawnKindDef[defName="GazelleManWarrior"]</xpath>
    <value>
      <li Class="CombatExtended.LoadoutPropertiesExtension">
        <primaryMagazineCount>
          <min>30</min>  <!-- single arrow count, not packs of arrows -->
          <max>50</max>
        </primaryMagazineCount>
      </li>
    </value>
  </Operation>

  <Operation Class="PatchOperationAddModExtension">
    <xpath>Defs/PawnKindDef[defName="GazelleManTrader"]</xpath>
    <value>
      <li Class="CombatExtended.LoadoutPropertiesExtension">
        <primaryMagazineCount>
          <min>30</min>  <!-- single arrow count, not packs of arrows -->
          <max>50</max>
        </primaryMagazineCount>
      </li>
    </value>
  </Operation>

  <Operation Class="PatchOperationAddModExtension">
    <xpath>Defs/PawnKindDef[defName="GazelleManArcher"]</xpath>
    <value>
      <li Class="CombatExtended.LoadoutPropertiesExtension">
        <primaryMagazineCount>
          <min>30</min>  <!-- single arrow count, not packs of arrows -->
          <max>50</max>
        </primaryMagazineCount>
      </li>
    </value>
  </Operation>

  <Operation Class="PatchOperationAddModExtension">
    <xpath>Defs/PawnKindDef[defName="GazelleManChief"]</xpath>
    <value>
      <li Class="CombatExtended.LoadoutPropertiesExtension">
        <primaryMagazineCount>
          <min>30</min>  <!-- single arrow count, not packs of arrows -->
          <max>50</max>
        </primaryMagazineCount>
      </li>
    </value>
  </Operation>

  <Operation Class="PatchOperationAddModExtension">
    <xpath>Defs/PawnKindDef[defName="LynxManWarrior"]</xpath>
    <value>
      <li Class="CombatExtended.LoadoutPropertiesExtension">
        <primaryMagazineCount>
          <min>30</min>  <!-- single arrow count, not packs of arrows -->
          <max>50</max>
        </primaryMagazineCount>
      </li>
    </value>
  </Operation>

  <Operation Class="PatchOperationAddModExtension">
    <xpath>Defs/PawnKindDef[defName="LynxManTrader"]</xpath>
    <value>
      <li Class="CombatExtended.LoadoutPropertiesExtension">
        <primaryMagazineCount>
          <min>30</min>  <!-- single arrow count, not packs of arrows -->
          <max>50</max>
        </primaryMagazineCount>
      </li>
    </value>
  </Operation>

  <Operation Class="PatchOperationAddModExtension">
    <xpath>Defs/PawnKindDef[defName="LynxManArcher"]</xpath>
    <value>
      <li Class="CombatExtended.LoadoutPropertiesExtension">
        <primaryMagazineCount>
          <min>30</min>  <!-- single arrow count, not packs of arrows -->
          <max>50</max>
        </primaryMagazineCount>
      </li>
    </value>
  </Operation>

  <Operation Class="PatchOperationAddModExtension">
    <xpath>Defs/PawnKindDef[defName="LynxManChief"]</xpath>
    <value>
      <li Class="CombatExtended.LoadoutPropertiesExtension">
        <primaryMagazineCount>
          <min>30</min>  <!-- single arrow count, not packs of arrows -->
          <max>50</max>
        </primaryMagazineCount>
      </li>
    </value>
  </Operation>

  <Operation Class="PatchOperationAddModExtension">
    <xpath>Defs/PawnKindDef[defName="PigManWarrior"]</xpath>
    <value>
      <li Class="CombatExtended.LoadoutPropertiesExtension">
        <primaryMagazineCount>
          <min>30</min>  <!-- single arrow count, not packs of arrows -->
          <max>50</max>
        </primaryMagazineCount>
      </li>
    </value>
  </Operation>

  <Operation Class="PatchOperationAddModExtension">
    <xpath>Defs/PawnKindDef[defName="PigManTrader"]</xpath>
    <value>
      <li Class="CombatExtended.LoadoutPropertiesExtension">
        <primaryMagazineCount>
          <min>30</min>  <!-- single arrow count, not packs of arrows -->
          <max>50</max>
        </primaryMagazineCount>
      </li>
    </value>
  </Operation>

  <Operation Class="PatchOperationAddModExtension">
    <xpath>Defs/PawnKindDef[defName="PigManArcher"]</xpath>
    <value>
      <li Class="CombatExtended.LoadoutPropertiesExtension">
        <primaryMagazineCount>
          <min>30</min>  <!-- single arrow count, not packs of arrows -->
          <max>50</max>
        </primaryMagazineCount>
      </li>
    </value>
  </Operation>

  <Operation Class="PatchOperationAddModExtension">
    <xpath>Defs/PawnKindDef[defName="PigManChief"]</xpath>
    <value>
      <li Class="CombatExtended.LoadoutPropertiesExtension">
        <primaryMagazineCount>
          <min>30</min>  <!-- single arrow count, not packs of arrows -->
          <max>50</max>
        </primaryMagazineCount>
      </li>
    </value>
  </Operation>

  <Operation Class="PatchOperationAddModExtension">
    <xpath>Defs/PawnKindDef[defName="RaccoonManWarrior"]</xpath>
    <value>
      <li Class="CombatExtended.LoadoutPropertiesExtension">
        <primaryMagazineCount>
          <min>30</min>  <!-- single arrow count, not packs of arrows -->
          <max>50</max>
        </primaryMagazineCount>
      </li>
    </value>
  </Operation>

  <Operation Class="PatchOperationAddModExtension">
    <xpath>Defs/PawnKindDef[defName="RaccoonManTrader"]</xpath>
    <value>
      <li Class="CombatExtended.LoadoutPropertiesExtension">
        <primaryMagazineCount>
          <min>30</min>  <!-- single arrow count, not packs of arrows -->
          <max>50</max>
        </primaryMagazineCount>
      </li>
    </value>
  </Operation>

  <Operation Class="PatchOperationAddModExtension">
    <xpath>Defs/PawnKindDef[defName="RaccoonManArcher"]</xpath>
    <value>
      <li Class="CombatExtended.LoadoutPropertiesExtension">
        <primaryMagazineCount>
          <min>30</min>  <!-- single arrow count, not packs of arrows -->
          <max>50</max>
        </primaryMagazineCount>
      </li>
    </value>
  </Operation>

  <Operation Class="PatchOperationAddModExtension">
    <xpath>Defs/PawnKindDef[defName="RaccoonManChief"]</xpath>
    <value>
      <li Class="CombatExtended.LoadoutPropertiesExtension">
        <primaryMagazineCount>
          <min>30</min>  <!-- single arrow count, not packs of arrows -->
          <max>50</max>
        </primaryMagazineCount>
      </li>
    </value>
  </Operation>

  <Operation Class="PatchOperationAddModExtension">
    <xpath>Defs/PawnKindDef[defName="WolfManWarrior"]</xpath>
    <value>
      <li Class="CombatExtended.LoadoutPropertiesExtension">
        <primaryMagazineCount>
          <min>30</min>  <!-- single arrow count, not packs of arrows -->
          <max>50</max>
        </primaryMagazineCount>
      </li>
    </value>
  </Operation>

  <Operation Class="PatchOperationAddModExtension">
    <xpath>Defs/PawnKindDef[defName="WolfManTrader"]</xpath>
    <value>
      <li Class="CombatExtended.LoadoutPropertiesExtension">
        <primaryMagazineCount>
          <min>30</min>  <!-- single arrow count, not packs of arrows -->
          <max>50</max>
        </primaryMagazineCount>
      </li>
    </value>
  </Operation>

  <Operation Class="PatchOperationAddModExtension">
    <xpath>Defs/PawnKindDef[defName="WolfManArcher"]</xpath>
    <value>
      <li Class="CombatExtended.LoadoutPropertiesExtension">
        <primaryMagazineCount>
          <min>30</min>  <!-- single arrow count, not packs of arrows -->
          <max>50</max>
        </primaryMagazineCount>
      </li>
    </value>
  </Operation>

  <Operation Class="PatchOperationAddModExtension">
    <xpath>Defs/PawnKindDef[defName="WolfManChief"]</xpath>
    <value>
      <li Class="CombatExtended.LoadoutPropertiesExtension">
        <primaryMagazineCount>
          <min>30</min>  <!-- single arrow count, not packs of arrows -->
          <max>50</max>
        </primaryMagazineCount>
      </li>
    </value>
  </Operation>

</Patch>

